MANIFEST.in
README.md
setup.py
adaletTextCleaner/__init__.py
adaletTextCleaner/myfunctions.py
adaletTextCleaner/utils.py
adaletTextCleaner.egg-info/PKG-INFO
adaletTextCleaner.egg-info/SOURCES.txt
adaletTextCleaner.egg-info/dependency_links.txt
adaletTextCleaner.egg-info/top_level.txt
adaletTextCleaner/resources/abbreviations.json
adaletTextCleaner/resources/adaletCommonWords.txt
adaletTextCleaner/resources/adaletUnusedWords.txt
adaletTextCleaner/resources/allowedChars.txt
adaletTextCleaner/resources/cleaningParams.txt
adaletTextCleaner/resources/il_ilceler.xml
adaletTextCleaner/resources/punctuations.txt
adaletTextCleaner/resources/stopwords.txt
adaletTextCleaner/resources/trCharToReplace.json
tests/__init__.py
tests/test_myfunctions.py